_fastcluster.cpython-311-x86_64-linux-gnu.so
fastcluster.py
fastcluster-1.3.0.dist-info/METADATA
fastcluster-1.3.0.dist-info/WHEEL
fastcluster-1.3.0.dist-info/top_level.txt
fastcluster-1.3.0.dist-info/RECORD
fastcluster-1.3.0.dist-info/licenses/COPYING.txt
