Metadata-Version: 2.4
Name: fastcluster
Version: 1.3.0
Summary: Fast hierarchical clustering routines for R and Python.
Home-page: https://danifold.net
Author: Daniel Müllner
Author-email: daniel@danifold.net
License: BSD-2-clause OR GPL-2.0-or-later
Keywords: dendrogram,linkage,cluster,agglomerative,hierarchical,hierarchy,ward
Classifier: Topic :: Scientific/Engineering :: Information Analysis
Classifier: Topic :: Scientific/Engineering :: Artificial Intelligence
Classifier: Topic :: Scientific/Engineering :: Bio-Informatics
Classifier: Topic :: Scientific/Engineering :: Mathematics
Classifier: Programming Language :: Python
Classifier: Programming Language :: Python :: 3
Classifier: Programming Language :: C++
Classifier: Operating System :: OS Independent
Classifier: License :: OSI Approved :: BSD License
Classifier: License :: OSI Approved :: GNU General Public License v2 (GPLv2)
Classifier: Intended Audience :: Science/Research
Classifier: Development Status :: 5 - Production/Stable
Requires: numpy
Provides: fastcluster
Requires-Python: >=3
License-File: COPYING.txt
Requires-Dist: numpy>=2
Dynamic: author
Dynamic: author-email
Dynamic: classifier
Dynamic: description
Dynamic: description-content-type
Dynamic: home-page
Dynamic: keywords
Dynamic: license
Dynamic: license-file
Dynamic: provides
Dynamic: requires
Dynamic: requires-dist
Dynamic: requires-python
Dynamic: summary
